Metadata-Version: 1.0
Name: ps-distributions
Version: 0.1
Summary: Gaussian and Binomial distributions
Home-page: UNKNOWN
Author: Parth Sheth
Author-email: parthsheth.nmims@gmail.com
License: UNKNOWN
Platform: UNKNOWN
